
{
  "header": {
    "reportVersion": 1,
    "event": "Allocation failed - JavaScript heap out of memory",
    "trigger": "FatalError",
    "filename": "report.20200623.233719.12318.0.001.json",
    "dumpEventTime": "2020-06-23T23:37:19Z",
    "dumpEventTimeStamp": "1592969839347",
    "processId": 12318,
    "cwd": "/Users/jumisanchez/Documents/codeim/term-1/week-5/whiling-away",
    "commandLine": [
      "/usr/local/Cellar/node/13.8.0/bin/node",
      "-r",
      "/Users/jumisanchez/.vscode/extensions/wallabyjs.quokka-vscode-1.0.301/dist/wallaby/node_modules/esm",
      "/Users/jumisanchez/.vscode/extensions/wallabyjs.quokka-vscode-1.0.301/dist/wallaby/server.js",
      "runner",
      "0",
      "56891",
      "quokka@1.0.0",
      "",
      "/Users/jumisanchez/Documents/codeim/term-1/week-5/whiling-away/node_modules",
      "quokka_fake_path/original",
      "",
      ""
    ],
    "nodejsVersion": "v13.8.0",
    "wordSize": 64,
    "arch": "x64",
    "platform": "darwin",
    "componentVersions": {
      "node": "13.8.0",
      "v8": "7.9.317.25-node.28",
      "uv": "1.34.1",
      "zlib": "1.2.11",
      "brotli": "1.0.7",
      "ares": "1.15.0",
      "modules": "79",
      "nghttp2": "1.40.0",
      "napi": "5",
      "llhttp": "2.0.4",
      "openssl": "1.1.1d",
      "cldr": "35.1",
      "icu": "64.2",
      "tz": "2019a",
      "unicode": "12.1"
    },
    "release": {
      "name": "node",
      "headersUrl": "https://nodejs.org/download/release/v13.8.0/node-v13.8.0-headers.tar.gz",
      "sourceUrl": "https://nodejs.org/download/release/v13.8.0/node-v13.8.0.tar.gz"
    },
    "osName": "Darwin",
    "osRelease": "19.3.0",
    "osVersion": "Darwin Kernel Version 19.3.0: Thu Jan  9 20:58:23 PST 2020; root:xnu-6153.81.5~1/RELEASE_X86_64",
    "osMachine": "x86_64",
    "cpus": [
      {
        "model": "Intel(R) Core(TM) i5-8257U CPU @ 1.40GHz",
        "speed": 1400,
        "user": 7181240,
        "nice": 0,
        "sys": 3698720,
        "idle": 29587590,
        "irq": 0
      },
      {
        "model": "Intel(R) Core(TM) i5-8257U CPU @ 1.40GHz",
        "speed": 1400,
        "user": 896890,
        "nice": 0,
        "sys": 533590,
        "idle": 39032820,
        "irq": 0
      },
      {
        "model": "Intel(R) Core(TM) i5-8257U CPU @ 1.40GHz",
        "speed": 1400,
        "user": 6868970,
        "nice": 0,
        "sys": 2637860,
        "idle": 30956710,
        "irq": 0
      },
      {
        "model": "Intel(R) Core(TM) i5-8257U CPU @ 1.40GHz",
        "speed": 1400,
        "user": 814990,
        "nice": 0,
        "sys": 406600,
        "idle": 39241690,
        "irq": 0
      },
      {
        "model": "Intel(R) Core(TM) i5-8257U CPU @ 1.40GHz",
        "speed": 1400,
        "user": 6089700,
        "nice": 0,
        "sys": 2145320,
        "idle": 32228500,
        "irq": 0
      },
      {
        "model": "Intel(R) Core(TM) i5-8257U CPU @ 1.40GHz",
        "speed": 1400,
        "user": 813580,
        "nice": 0,
        "sys": 359450,
        "idle": 39290240,
        "irq": 0
      },
      {
        "model": "Intel(R) Core(TM) i5-8257U CPU @ 1.40GHz",
        "speed": 1400,
        "user": 5276180,
        "nice": 0,
        "sys": 1752960,
        "idle": 33434360,
        "irq": 0
      },
      {
        "model": "Intel(R) Core(TM) i5-8257U CPU @ 1.40GHz",
        "speed": 1400,
        "user": 854360,
        "nice": 0,
        "sys": 325870,
        "idle": 39283030,
        "irq": 0
      }
    ],
    "networkInterfaces": [
      {
        "name": "lo0",
        "internal": true,
        "mac": "00:00:00:00:00:00",
        "address": "127.0.0.1",
        "netmask": "255.0.0.0",
        "family": "IPv4"
      },
      {
        "name": "lo0",
        "internal": true,
        "mac": "00:00:00:00:00:00",
        "address": "::1",
        "netmask": "ffff:ffff:ffff:ffff:ffff:ffff:ffff:ffff",
        "family": "IPv6",
        "scopeid": 0
      },
      {
        "name": "lo0",
        "internal": true,
        "mac": "00:00:00:00:00:00",
        "address": "fe80::1",
        "netmask": "ffff:ffff:ffff:ffff::",
        "family": "IPv6",
        "scopeid": 1
      },
      {
        "name": "en3",
        "internal": false,
        "mac": "ac:de:48:00:11:22",
        "address": "fe80::aede:48ff:fe00:1122",
        "netmask": "ffff:ffff:ffff:ffff::",
        "family": "IPv6",
        "scopeid": 4
      },
      {
        "name": "en0",
        "internal": false,
        "mac": "f8:ff:c2:43:32:b8",
        "address": "fe80::43:c036:610b:ec78",
        "netmask": "ffff:ffff:ffff:ffff::",
        "family": "IPv6",
        "scopeid": 6
      },
      {
        "name": "en0",
        "internal": false,
        "mac": "f8:ff:c2:43:32:b8",
        "address": "fd4b:8d38:69ba:1:cc7:211f:5d93:980e",
        "netmask": "ffff:ffff:ffff:ffff::",
        "family": "IPv6",
        "scopeid": 0
      },
      {
        "name": "en0",
        "internal": false,
        "mac": "f8:ff:c2:43:32:b8",
        "address": "fd4b:8d38:69ba:1:7d1a:96fd:546e:544b",
        "netmask": "ffff:ffff:ffff:ffff::",
        "family": "IPv6",
        "scopeid": 0
      },
      {
        "name": "en0",
        "internal": false,
        "mac": "f8:ff:c2:43:32:b8",
        "address": "192.168.1.2",
        "netmask": "255.255.255.0",
        "family": "IPv4"
      },
      {
        "name": "awdl0",
        "internal": false,
        "mac": "f2:b7:c7:2d:10:03",
        "address": "fe80::f0b7:c7ff:fe2d:1003",
        "netmask": "ffff:ffff:ffff:ffff::",
        "family": "IPv6",
        "scopeid": 11
      },
      {
        "name": "llw0",
        "internal": false,
        "mac": "f2:b7:c7:2d:10:03",
        "address": "fe80::f0b7:c7ff:fe2d:1003",
        "netmask": "ffff:ffff:ffff:ffff::",
        "family": "IPv6",
        "scopeid": 12
      },
      {
        "name": "utun0",
        "internal": false,
        "mac": "00:00:00:00:00:00",
        "address": "fe80::262:140c:ad70:d4c7",
        "netmask": "ffff:ffff:ffff:ffff::",
        "family": "IPv6",
        "scopeid": 13
      },
      {
        "name": "utun1",
        "internal": false,
        "mac": "00:00:00:00:00:00",
        "address": "fe80::fbec:b7fc:2af8:6f95",
        "netmask": "ffff:ffff:ffff:ffff::",
        "family": "IPv6",
        "scopeid": 14
      }
    ],
    "host": "Jumis-MBP.home"
  },
  "javascriptStack": {
    "message": "No stack.",
    "stack": [
      "Unavailable."
    ]
  },
  "nativeStack": [
    {
      "pc": "0x000000010015c853",
      "symbol": "report::TriggerNodeReport(v8::Isolate*, node::Environment*, char const*, char const*, std::__1::basic_string<char, std::__1::char_traits<char>, std::__1::allocator<char> > const&, v8::Local<v8::String>) [/usr/local/Cellar/node/13.8.0/bin/node]"
    },
    {
      "pc": "0x0000000100084a58",
      "symbol": "node::OnFatalError(char const*, char const*) [/usr/local/Cellar/node/13.8.0/bin/node]"
    },
    {
      "pc": "0x000000010017fa4d",
      "symbol": "v8::Utils::ReportOOMFailure(v8::internal::Isolate*, char const*, bool) [/usr/local/Cellar/node/13.8.0/bin/node]"
    },
    {
      "pc": "0x000000010017f9f7",
      "symbol": "v8::internal::V8::FatalProcessOutOfMemory(v8::internal::Isolate*, char const*, bool) [/usr/local/Cellar/node/13.8.0/bin/node]"
    },
    {
      "pc": "0x0000000100299baf",
      "symbol": "v8::internal::Heap::FatalProcessOutOfMemory(char const*) [/usr/local/Cellar/node/13.8.0/bin/node]"
    },
    {
      "pc": "0x000000010029af4c",
      "symbol": "v8::internal::Heap::MarkCompactPrologue() [/usr/local/Cellar/node/13.8.0/bin/node]"
    },
    {
      "pc": "0x0000000100298b04",
      "symbol": "v8::internal::Heap::PerformGarbageCollection(v8::internal::GarbageCollector, v8::GCCallbackFlags) [/usr/local/Cellar/node/13.8.0/bin/node]"
    },
    {
      "pc": "0x00000001002975ab",
      "symbol": "v8::internal::Heap::CollectGarbage(v8::internal::AllocationSpace, v8::internal::GarbageCollectionReason, v8::GCCallbackFlags) [/usr/local/Cellar/node/13.8.0/bin/node]"
    },
    {
      "pc": "0x000000010029eff8",
      "symbol": "v8::internal::Heap::AllocateRawWithLightRetrySlowPath(int, v8::internal::AllocationType, v8::internal::AllocationOrigin, v8::internal::AllocationAlignment) [/usr/local/Cellar/node/13.8.0/bin/node]"
    },
    {
      "pc": "0x000000010029f04e",
      "symbol": "v8::internal::Heap::AllocateRawWithRetryOrFailSlowPath(int, v8::internal::AllocationType, v8::internal::AllocationOrigin, v8::internal::AllocationAlignment) [/usr/local/Cellar/node/13.8.0/bin/node]"
    },
    {
      "pc": "0x000000010027cbbf",
      "symbol": "v8::internal::Factory::NewFillerObject(int, bool, v8::internal::AllocationType, v8::internal::AllocationOrigin) [/usr/local/Cellar/node/13.8.0/bin/node]"
    },
    {
      "pc": "0x00000001004e1b3f",
      "symbol": "v8::internal::Runtime_AllocateInYoungGeneration(int, unsigned long*, v8::internal::Isolate*) [/usr/local/Cellar/node/13.8.0/bin/node]"
    },
    {
      "pc": "0x00000001007502f9",
      "symbol": "Builtins_CEntry_Return1_DontSaveFPRegs_ArgvOnStack_NoBuiltinExit [/usr/local/Cellar/node/13.8.0/bin/node]"
    },
    {
      "pc": "0x00000001006ddada",
      "symbol": "Builtins_GrowFastSmiOrObjectElements [/usr/local/Cellar/node/13.8.0/bin/node]"
    }
  ],
  "javascriptHeap": {
    "totalMemory": 2154033152,
    "totalCommittedMemory": 2150562576,
    "usedMemory": 2146899504,
    "availableMemory": 47702096,
    "memoryLimit": 2197815296,
    "heapSpaces": {
      "read_only_space": {
        "memorySize": 262144,
        "committedMemory": 33328,
        "capacity": 33040,
        "used": 33040,
        "available": 0
      },
      "new_space": {
        "memorySize": 4194304,
        "committedMemory": 1536960,
        "capacity": 2094848,
        "used": 549984,
        "available": 1544864
      },
      "old_space": {
        "memorySize": 2092572672,
        "committedMemory": 2092299600,
        "capacity": 2090168944,
        "used": 2089888704,
        "available": 280240
      },
      "code_space": {
        "memorySize": 430080,
        "committedMemory": 380608,
        "capacity": 357856,
        "used": 357856,
        "available": 0
      },
      "map_space": {
        "memorySize": 1052672,
        "committedMemory": 790800,
        "capacity": 608880,
        "used": 608880,
        "available": 0
      },
      "large_object_space": {
        "memorySize": 55472128,
        "committedMemory": 55472128,
        "capacity": 55458256,
        "used": 55458256,
        "available": 0
      },
      "code_large_object_space": {
        "memorySize": 49152,
        "committedMemory": 49152,
        "capacity": 2784,
        "used": 2784,
        "available": 0
      },
      "new_large_object_space": {
        "memorySize": 0,
        "committedMemory": 0,
        "capacity": 2094848,
        "used": 0,
        "available": 2094848
      }
    }
  },
  "resourceUsage": {
    "userCpuSeconds": 71.2705,
    "kernelCpuSeconds": 2.46574,
    "cpuConsumptionPercent": 179.844,
    "maxRss": 2319232008192,
    "pageFaults": {
      "IORequired": 27,
      "IONotRequired": 715842
    },
    "fsActivity": {
      "reads": 0,
      "writes": 0
    }
  },
  "libuv": [
  ],
  "environmentVariables": {
    "USER": "jumisanchez",
    "PATH": "/usr/local/bin:/usr/bin:/bin:/usr/sbin:/sbin:/usr/local/bin:/usr/bin",
    "LOGNAME": "jumisanchez",
    "SSH_AUTH_SOCK": "/private/tmp/com.apple.launchd.RxtntnQKSs/Listeners",
    "HOME": "/Users/jumisanchez",
    "SHELL": "/bin/zsh",
    "__CF_USER_TEXT_ENCODING": "0x1F5:0x0:0x0",
    "TMPDIR": "/var/folders/cs/ntymkx1s05196q7nm75mgff80000gn/T/",
    "XPC_SERVICE_NAME": "com.microsoft.VSCode.8320",
    "XPC_FLAGS": "0x0",
    "ORIGINAL_XDG_CURRENT_DESKTOP": "undefined",
    "VSCODE_NLS_CONFIG": "{\"locale\":\"en-us\",\"availableLanguages\":{},\"_languagePackSupport\":true}",
    "VSCODE_NODE_CACHED_DATA_DIR": "/Users/jumisanchez/Library/Application Support/Code/CachedData/cd9ea6488829f560dc949a8b2fb789f3cdc05f5d",
    "VSCODE_LOGS": "/Users/jumisanchez/Library/Application Support/Code/logs/20200623T225052",
    "VSCODE_IPC_HOOK": "/Users/jumisanchez/Library/Application Support/Code/1.46.1-main.sock",
    "VSCODE_PID": "9437",
    "LESS": "-R",
    "LSCOLORS": "Gxfxcxdxbxegedabagacad",
    "OLDPWD": "/",
    "PAGER": "less",
    "PWD": "/Users/jumisanchez/Documents/codeim/term-1/week-5/whiling-away",
    "SHLVL": "0",
    "ZSH": "/Users/jumisanchez/.oh-my-zsh",
    "_": "/Applications/Visual Studio Code 3.app/Contents/MacOS/Electron",
    "AMD_ENTRYPOINT": "vs/workbench/services/extensions/node/extensionHostProcess",
    "PIPE_LOGGING": "true",
    "VERBOSE_LOGGING": "true",
    "VSCODE_IPC_HOOK_EXTHOST": "/var/folders/cs/ntymkx1s05196q7nm75mgff80000gn/T/vscode-ipc-24878047-3414-446f-928c-fdd6271cf7b6.sock",
    "VSCODE_HANDLES_UNCAUGHT_ERRORS": "true",
    "VSCODE_LOG_STACK": "false",
    "APPLICATION_INSIGHTS_NO_DIAGNOSTIC_CHANNEL": "true",
    "WALLABY_PRODUCTION": "true",
    "WALLABY_USE_WSL": "false",
    "DEBUG": "wallaby:.*",
    "DEBUG_COLORS": "no",
    "quokka": "{\"globalConfigFile\":\"/Users/jumisanchez/.quokka/config.json\",\"tempDir\":\"/Users/jumisanchez/.quokka/data/82s1t\",\"pro\":false,\"stdEsm\":true}",
    "undefined": "",
    "ESM_OPTIONS": "{\"await\":true}",
    "WALLABY_ENV": "true"
  },
  "userLimits": {
    "core_file_size_blocks": {
      "soft": 0,
      "hard": "unlimited"
    },
    "data_seg_size_kbytes": {
      "soft": "unlimited",
      "hard": "unlimited"
    },
    "file_size_blocks": {
      "soft": "unlimited",
      "hard": "unlimited"
    },
    "max_locked_memory_bytes": {
      "soft": "unlimited",
      "hard": "unlimited"
    },
    "max_memory_size_kbytes": {
      "soft": "unlimited",
      "hard": "unlimited"
    },
    "open_files": {
      "soft": 24576,
      "hard": "unlimited"
    },
    "stack_size_bytes": {
      "soft": 8388608,
      "hard": 67104768
    },
    "cpu_time_seconds": {
      "soft": "unlimited",
      "hard": "unlimited"
    },
    "max_user_processes": {
      "soft": 2784,
      "hard": 4176
    },
    "virtual_memory_kbytes": {
      "soft": "unlimited",
      "hard": "unlimited"
    }
  },
  "sharedObjects": [
    "/usr/local/Cellar/node/13.8.0/bin/node",
    "/usr/local/opt/icu4c/lib/libicui18n.64.dylib",
    "/usr/local/opt/icu4c/lib/libicuuc.64.dylib",
    "/usr/local/opt/icu4c/lib/libicudata.64.dylib",
    "/System/Library/Frameworks/CoreFoundation.framework/Versions/A/CoreFoundation",
    "/usr/lib/libSystem.B.dylib",
    "/usr/lib/libc++.1.dylib",
    "/usr/lib/system/libcache.dylib",
    "/usr/lib/system/libcommonCrypto.dylib",
    "/usr/lib/system/libcompiler_rt.dylib",
    "/usr/lib/system/libcopyfile.dylib",
    "/usr/lib/system/libcorecrypto.dylib",
    "/usr/lib/system/libdispatch.dylib",
    "/usr/lib/system/libdyld.dylib",
    "/usr/lib/system/libkeymgr.dylib",
    "/usr/lib/system/liblaunch.dylib",
    "/usr/lib/system/libmacho.dylib",
    "/usr/lib/system/libquarantine.dylib",
    "/usr/lib/system/libremovefile.dylib",
    "/usr/lib/system/libsystem_asl.dylib",
    "/usr/lib/system/libsystem_blocks.dylib",
    "/usr/lib/system/libsystem_c.dylib",
    "/usr/lib/system/libsystem_configuration.dylib",
    "/usr/lib/system/libsystem_coreservices.dylib",
    "/usr/lib/system/libsystem_darwin.dylib",
    "/usr/lib/system/libsystem_dnssd.dylib",
    "/usr/lib/system/libsystem_featureflags.dylib",
    "/usr/lib/system/libsystem_info.dylib",
    "/usr/lib/system/libsystem_m.dylib",
    "/usr/lib/system/libsystem_malloc.dylib",
    "/usr/lib/system/libsystem_networkextension.dylib",
    "/usr/lib/system/libsystem_notify.dylib",
    "/usr/lib/system/libsystem_sandbox.dylib",
    "/usr/lib/system/libsystem_secinit.dylib",
    "/usr/lib/system/libsystem_kernel.dylib",
    "/usr/lib/system/libsystem_platform.dylib",
    "/usr/lib/system/libsystem_pthread.dylib",
    "/usr/lib/system/libsystem_symptoms.dylib",
    "/usr/lib/system/libsystem_trace.dylib",
    "/usr/lib/system/libunwind.dylib",
    "/usr/lib/system/libxpc.dylib",
    "/usr/lib/libobjc.A.dylib",
    "/usr/lib/libc++abi.dylib",
    "/usr/lib/libfakelink.dylib",
    "/usr/lib/libDiagnosticMessagesClient.dylib",
    "/usr/lib/libicucore.A.dylib",
    "/usr/lib/libz.1.dylib"
  ]
}